odoo/addons/ssi_accountant_report/README.rst
odoo/addons/ssi_accountant_report/__init__.py
odoo/addons/ssi_accountant_report/__manifest__.py
odoo/addons/ssi_accountant_report/menu.xml
odoo/addons/ssi_accountant_report/data/approval_template_data.xml
odoo/addons/ssi_accountant_report/data/ir_sequence_data.xml
odoo/addons/ssi_accountant_report/data/policy_template_data.xml
odoo/addons/ssi_accountant_report/data/sequence_template_data.xml
odoo/addons/ssi_accountant_report/models/__init__.py
odoo/addons/ssi_accountant_report/models/accountant_assurance_report.py
odoo/addons/ssi_accountant_report/models/accountant_nonassurance_report.py
odoo/addons/ssi_accountant_report/models/accountant_report_mixin.py
odoo/addons/ssi_accountant_report/models/accountant_service.py
odoo/addons/ssi_accountant_report/models/company_public_offering_type.py
odoo/addons/ssi_accountant_report/security/ir.model.access.csv
odoo/addons/ssi_accountant_report/security/ir_module_category_data.xml
odoo/addons/ssi_accountant_report/security/ir_rule_data.xml
odoo/addons/ssi_accountant_report/security/res_group_data.xml
odoo/addons/ssi_accountant_report/static/description/icon.png
odoo/addons/ssi_accountant_report/views/accountant_assurance_report_views.xml
odoo/addons/ssi_accountant_report/views/accountant_nonassurance_report_views.xml
odoo/addons/ssi_accountant_report/views/accountant_report_mixin_views.xml
odoo/addons/ssi_accountant_report/views/accountant_service_views.xml
odoo/addons/ssi_accountant_report/views/company_public_offering_type_views.xml
odoo14_addon_ssi_accountant_report-14.0.2.0.1.dist-info/METADATA
odoo14_addon_ssi_accountant_report-14.0.2.0.1.dist-info/WHEEL
odoo14_addon_ssi_accountant_report-14.0.2.0.1.dist-info/top_level.txt
odoo14_addon_ssi_accountant_report-14.0.2.0.1.dist-info/RECORD
